{"errors":[],"warnings":[],"namedChunkGroups":{"polyfill":{"chunks":[3,0,12],"assets":["webpack-runtime-a96ed12f9be6e244193c.js","webpack-runtime-a96ed12f9be6e244193c.js.map","commons-374b848efa331418b2b2.js","commons-374b848efa331418b2b2.js.map","polyfill-d562fb213b843530b0af.js","polyfill-d562fb213b843530b0af.js.map"],"children":{},"childAssets":{}},"app":{"chunks":[3,11,4],"assets":["webpack-runtime-a96ed12f9be6e244193c.js","webpack-runtime-a96ed12f9be6e244193c.js.map","framework-85aff51d15c28c7fbe5f.js","framework-85aff51d15c28c7fbe5f.js.map","app-64eef3d4cb00e0ba4e26.js","app-64eef3d4cb00e0ba4e26.js.map"],"children":{},"childAssets":{}},"component---src-pages-404-js":{"chunks":[2,1,0,5],"assets":["styles.be04124f392f05c04b68.css","styles-2d82ac8e3afc0c213061.js","styles-2d82ac8e3afc0c213061.js.map","1bfc9850-a24f2ba2bf7d9bccb531.js","1bfc9850-a24f2ba2bf7d9bccb531.js.map","commons-374b848efa331418b2b2.js","commons-374b848efa331418b2b2.js.map","component---src-pages-404-js-60248b543f79300f3d02.js","component---src-pages-404-js-60248b543f79300f3d02.js.map"],"children":{},"childAssets":{}},"component---src-pages-bio-js":{"chunks":[2,1,0,6],"assets":["styles.be04124f392f05c04b68.css","styles-2d82ac8e3afc0c213061.js","styles-2d82ac8e3afc0c213061.js.map","1bfc9850-a24f2ba2bf7d9bccb531.js","1bfc9850-a24f2ba2bf7d9bccb531.js.map","commons-374b848efa331418b2b2.js","commons-374b848efa331418b2b2.js.map","component---src-pages-bio-js-543b05ca12ce8be9bbeb.js","component---src-pages-bio-js-543b05ca12ce8be9bbeb.js.map"],"children":{},"childAssets":{}},"component---src-pages-book-js":{"chunks":[2,1,0,7],"assets":["styles.be04124f392f05c04b68.css","styles-2d82ac8e3afc0c213061.js","styles-2d82ac8e3afc0c213061.js.map","1bfc9850-a24f2ba2bf7d9bccb531.js","1bfc9850-a24f2ba2bf7d9bccb531.js.map","commons-374b848efa331418b2b2.js","commons-374b848efa331418b2b2.js.map","component---src-pages-book-js-7e623cf783a6bfc4efd7.js","component---src-pages-book-js-7e623cf783a6bfc4efd7.js.map"],"children":{},"childAssets":{}},"component---src-pages-contact-js":{"chunks":[2,1,0,8],"assets":["styles.be04124f392f05c04b68.css","styles-2d82ac8e3afc0c213061.js","styles-2d82ac8e3afc0c213061.js.map","1bfc9850-a24f2ba2bf7d9bccb531.js","1bfc9850-a24f2ba2bf7d9bccb531.js.map","commons-374b848efa331418b2b2.js","commons-374b848efa331418b2b2.js.map","component---src-pages-contact-js-9aaee7dea259bdd35626.js","component---src-pages-contact-js-9aaee7dea259bdd35626.js.map"],"children":{},"childAssets":{}},"component---src-pages-index-js":{"chunks":[2,1,0,9],"assets":["styles.be04124f392f05c04b68.css","styles-2d82ac8e3afc0c213061.js","styles-2d82ac8e3afc0c213061.js.map","1bfc9850-a24f2ba2bf7d9bccb531.js","1bfc9850-a24f2ba2bf7d9bccb531.js.map","commons-374b848efa331418b2b2.js","commons-374b848efa331418b2b2.js.map","component---src-pages-index-js-8a797dd5ab04353da7a3.js","component---src-pages-index-js-8a797dd5ab04353da7a3.js.map"],"children":{},"childAssets":{}},"component---src-pages-using-typescript-tsx":{"chunks":[2,1,0,10],"assets":["styles.be04124f392f05c04b68.css","styles-2d82ac8e3afc0c213061.js","styles-2d82ac8e3afc0c213061.js.map","1bfc9850-a24f2ba2bf7d9bccb531.js","1bfc9850-a24f2ba2bf7d9bccb531.js.map","commons-374b848efa331418b2b2.js","commons-374b848efa331418b2b2.js.map","component---src-pages-using-typescript-tsx-76c8646619904b84f47f.js","component---src-pages-using-typescript-tsx-76c8646619904b84f47f.js.map"],"children":{},"childAssets":{}}},"assetsByChunkName":{"polyfill":["webpack-runtime-a96ed12f9be6e244193c.js","commons-374b848efa331418b2b2.js","polyfill-d562fb213b843530b0af.js"],"app":["webpack-runtime-a96ed12f9be6e244193c.js","framework-85aff51d15c28c7fbe5f.js","app-64eef3d4cb00e0ba4e26.js"],"component---src-pages-404-js":["styles.be04124f392f05c04b68.css","styles-2d82ac8e3afc0c213061.js","1bfc9850-a24f2ba2bf7d9bccb531.js","commons-374b848efa331418b2b2.js","component---src-pages-404-js-60248b543f79300f3d02.js"],"component---src-pages-bio-js":["styles.be04124f392f05c04b68.css","styles-2d82ac8e3afc0c213061.js","1bfc9850-a24f2ba2bf7d9bccb531.js","commons-374b848efa331418b2b2.js","component---src-pages-bio-js-543b05ca12ce8be9bbeb.js"],"component---src-pages-book-js":["styles.be04124f392f05c04b68.css","styles-2d82ac8e3afc0c213061.js","1bfc9850-a24f2ba2bf7d9bccb531.js","commons-374b848efa331418b2b2.js","component---src-pages-book-js-7e623cf783a6bfc4efd7.js"],"component---src-pages-contact-js":["styles.be04124f392f05c04b68.css","styles-2d82ac8e3afc0c213061.js","1bfc9850-a24f2ba2bf7d9bccb531.js","commons-374b848efa331418b2b2.js","component---src-pages-contact-js-9aaee7dea259bdd35626.js"],"component---src-pages-index-js":["styles.be04124f392f05c04b68.css","styles-2d82ac8e3afc0c213061.js","1bfc9850-a24f2ba2bf7d9bccb531.js","commons-374b848efa331418b2b2.js","component---src-pages-index-js-8a797dd5ab04353da7a3.js"],"component---src-pages-using-typescript-tsx":["styles.be04124f392f05c04b68.css","styles-2d82ac8e3afc0c213061.js","1bfc9850-a24f2ba2bf7d9bccb531.js","commons-374b848efa331418b2b2.js","component---src-pages-using-typescript-tsx-76c8646619904b84f47f.js"]}}